{
  "project_info": {
    "project_number": "131159071265",
    "project_id": "hoard-7e21d",
    "storage_bucket": "hoard-7e21d.appspot.com"
  },
  "client": [
    {
      "client_info": {
        "mobilesdk_app_id": "1:131159071265:android:1e0fcc0aee22f53a2b2160",
        "android_client_info": {
          "package_name": "com.example.hoard"
        }
      },
      "oauth_client": [
        {
          "client_id": "131159071265-osb5pg6s3fb994b1q6tnscujeb45h6mr.apps.googleusercontent.com",
          "client_type": 1,
          "android_info": {
            "package_name": "com.example.hoard",
            "certificate_hash": "456492c7095c5342cc05f06587ce91bffb588da8"
          }
        },
        {
          "client_id": "131159071265-5hih16uja4pfq4gsd3mclhk1sioamv7l.apps.googleusercontent.com",
          "client_type": 3
        }
      ],
      "api_key": [
        {
          "current_key": "AIzaSyDY2spZhQKbabOzde2yBkdBRRpjTOjqR2A"
        }
      ],
      "services": {
        "appinvite_service": {
          "other_platform_oauth_client": [
            {
              "client_id": "131159071265-5hih16uja4pfq4gsd3mclhk1sioamv7l.apps.googleusercontent.com",
              "client_type": 3
            }
          ]
        }
      }
    }
  ],
  "configuration_version": "1"
}